<manifest>
	<grammars>
		<grammar>
			<url>https://github.com/melance/TheRandomizerWPFCustomizations/blob/master/Grammars/Deities.zip?raw=true</url>
			<name>Deities</name>
			<description>Generates a deity name and domains. Includes libraries for deities based on 14 different cultures.</description>
			<author>Lance Boudreaux</author>
			<tags>
				<tag>Deity</tag>
				<tag>Name</tag>
			</tags>
		</grammar>		
	</grammars>
	<libraries>
		<library>
			<url>https://raw.githubusercontent.com/melance/TheRandomizerWPFCustomizations/master/Libraries/korean_pheonome.lib.xml</url>
			<name>Korean Phonemes</name>
			<description>A list of Korean language phonemes</description>
			<author>/u/maxelliot</author>
		</library>
	</libraries>
	<themes>
	
	</themes>
	<templates>
		<template>
			<url>https://raw.githubusercontent.com/melance/TheRandomizerWPFCustomizations/master/Templates/The%20Randomizer%20Finger%20Text%20Snippets.ftd</url>
			<name>Notepad++ Finger Text Grammar Templates</name>
			<author>Lance Boudreaux</author>
		</template>
	</templates>
</manifest>
