<?xml version="1.0"?>
<library xmlns:xsd="http://www.w3.org/2001/XMLSchema" xmlns:xsi="http://www.w3.org/2001/XMLSchema-instance">
  <item name="koreanpheonome">a</item>
  <item name="koreanpheonome">ya</item>
  <item name="koreanpheonome">eo</item>
  <item name="koreanpheonome">yeo</item>
  <item name="koreanpheonome">ae</item>
  <item name="koreanpheonome">e</item>
  <item name="koreanpheonome">yae</item>
  <item name="koreanpheonome">ye</item>
  <item name="koreanpheonome">o</item>
  <item name="koreanpheonome">wa</item>
  <item name="koreanpheonome">yo</item>
  <item name="koreanpheonome">u</item>
  <item name="koreanpheonome">weo</item>
  <item name="koreanpheonome">wae</item>
  <item name="koreanpheonome">we</item>
  <item name="koreanpheonome">oe</item>
  <item name="koreanpheonome">wi</item>
  <item name="koreanpheonome">eu</item>
  <item name="koreanpheonome">eui</item>
  <item name="koreanpheonome">I</item>
  <item name="koreanpheonome">g</item>
  <item name="koreanpheonome">gg</item>
  <item name="koreanpheonome">n</item>
  <item name="koreanpheonome">d</item>
  <item name="koreanpheonome">dd</item>
  <item name="koreanpheonome">r</item>
  <item name="koreanpheonome">l</item>
  <item name="koreanpheonome">m</item>
  <item name="koreanpheonome">b</item>
  <item name="koreanpheonome">bb</item>
  <item name="koreanpheonome">s</item>
  <item name="koreanpheonome">sh</item>
  <item name="koreanpheonome">ss</item>
  <item name="koreanpheonome">-</item>
  <item name="koreanpheonome">j</item>
  <item name="koreanpheonome">jj</item>
  <item name="koreanpheonome">ch</item>
  <item name="koreanpheonome">k</item>
  <item name="koreanpheonome">t</item>
  <item name="koreanpheonome">p</item>
  <item name="koreanpheonome">h</item>
  <item name="koreanpheonome">er</item>
  <item name="koreanpheonome">C </item>
  <item name="koreanpheonome">Z</item>
  <item name="koreanpheonome">F</item>
  <item name="koreanpheonome">V</item>
  <item name="koreanpheonome">gp</item>
  <item name="koreanpheonome">np</item>
  <item name="koreanpheonome">dp</item>
  <item name="koreanpheonome">rp</item>
  <item name="koreanpheonome">mp</item>
  <item name="koreanpheonome">bp</item>
  <item name="koreanpheonome">Np</item>
</library>